fitconnect_client/__init__.py
fitconnect_client/client.py
fitconnect_client/crypto.py
fitconnect_client/environment.py
fitconnect_client/log.py
fitconnect_client/objects/__init__.py
fitconnect_client/objects/attachment.py
fitconnect_client/objects/exception.py
fitconnect_client/objects/submission.py
fitconnect_client-0.1.3.dist-info/LICENSE
fitconnect_client-0.1.3.dist-info/METADATA
fitconnect_client-0.1.3.dist-info/WHEEL
fitconnect_client-0.1.3.dist-info/top_level.txt
fitconnect_client-0.1.3.dist-info/RECORD
