Metadata-Version: 2.1
Name: fitconnect_client
Version: 0.1.3
Summary: A python SDK to interact with the German Fitconnect system
Author: Jon Bulica
Author-email: jonbulica99@gmail.com
License-File: LICENSE
Requires-Dist: urllib3
Requires-Dist: requests
Requires-Dist: jwcrypto
